MANIFEST.in
README.rst
setup.py
docs/HISTORY.txt
docs/LICENSE.GPL
docs/LICENSE.txt
pas/__init__.py
pas.plugins.trustedproxyauth.egg-info/PKG-INFO
pas.plugins.trustedproxyauth.egg-info/SOURCES.txt
pas.plugins.trustedproxyauth.egg-info/dependency_links.txt
pas.plugins.trustedproxyauth.egg-info/entry_points.txt
pas.plugins.trustedproxyauth.egg-info/namespace_packages.txt
pas.plugins.trustedproxyauth.egg-info/not-zip-safe
pas.plugins.trustedproxyauth.egg-info/requires.txt
pas.plugins.trustedproxyauth.egg-info/top_level.txt
pas/plugins/__init__.py
pas/plugins/trustedproxyauth/__init__.py
pas/plugins/trustedproxyauth/configure.zcml
pas/plugins/trustedproxyauth/plugin.py
pas/plugins/trustedproxyauth/testing.py
pas/plugins/trustedproxyauth/Extensions/__init__.py
pas/plugins/trustedproxyauth/Extensions/install.py
pas/plugins/trustedproxyauth/tests/__init__.py
pas/plugins/trustedproxyauth/tests/base.py
pas/plugins/trustedproxyauth/tests/test_pass_plugin.py
pas/plugins/trustedproxyauth/www/addPlugin.zpt
pas/plugins/trustedproxyauth/www/config.zpt