Metadata-Version: 2.1
Name: pas.plugins.trustedproxyauth
Version: 1.3.0
Summary: Authenticates requests coming from a reverse proxy doing user authentication.
Home-page: https://github.com/4teamwork/pas.plugins.trustedproxyauth
Author: 4teamwork AG
Author-email: mailto:info@4teamwork.ch
Maintainer: Thomas Buchberger
License: GPL2
Keywords: pas plugins trusted proxy auth plone
Platform: UNKNOWN
Classifier: Framework :: Plone
Classifier: Framework :: Plone :: 4.2
Classifier: Framework :: Plone :: 5.1
Classifier: Programming Language :: Python
Classifier: Topic :: Software Development :: Libraries :: Python Modules
Provides-Extra: tests
